diskcachedb/__init__.py
diskcachedb/db.py
diskcachedb/viewer.py
diskcachedb/templates/base.html
diskcachedb/templates/documents.html
diskcachedb/templates/error.html
diskcachedb/templates/index.html
diskcachedb/templates/query.html
diskcachedb-0.1.1.dist-info/licenses/LICENSE
tests/__init__.py
tests/test_db.py
diskcachedb-0.1.1.dist-info/METADATA
diskcachedb-0.1.1.dist-info/WHEEL
diskcachedb-0.1.1.dist-info/top_level.txt
diskcachedb-0.1.1.dist-info/RECORD
