Metadata-Version: 2.4
Name: diskcachedb
Version: 0.1.1
Summary: A MongoDB-like query interface using diskcache for persistent storage
Home-page: https://github.com/anandanklnce/diskcache-db
Author: Anandan B S
Author-email: anandanklnce@gmail.com
Keywords: database,cache,mongodb,diskcache,persistent storage,query
Classifier: Development Status :: 4 - Beta
Classifier: Intended Audience :: Developers
Classifier: Topic :: Database :: Database Engines/Servers
Classifier: Programming Language :: Python :: 3.7
Classifier: Programming Language :: Python :: 3.8
Classifier: Programming Language :: Python :: 3.9
Classifier: Programming Language :: Python :: 3.10
Classifier: Programming Language :: Python :: 3.11
Classifier: License :: OSI Approved :: MIT License
Classifier: Operating System :: OS Independent
Requires-Python: >=3.7
License-File: LICENSE
Requires-Dist: diskcache>=5.6.1
Requires-Dist: bson>=0.5.10
Requires-Dist: flask>=2.0.0
Dynamic: author
Dynamic: author-email
Dynamic: classifier
Dynamic: description
Dynamic: description-content-type
Dynamic: home-page
Dynamic: keywords
Dynamic: license-file
Dynamic: requires-dist
Dynamic: requires-python
Dynamic: summary
